fpiper.py
fpiper-0.0.1.dist-info/LICENSE
fpiper-0.0.1.dist-info/WHEEL
fpiper-0.0.1.dist-info/METADATA
fpiper-0.0.1.dist-info/RECORD
