Metadata-Version: 2.1
Name: fpiper
Version: 0.0.1
Summary: A small library providing functional wrappers over Optional and Iterable
License: MIT
Author: Vladimir Okhotnikov
Author-email: vokhotnikov@gmail.com
Requires-Python: >=3.9,<4.0
Classifier: License :: OSI Approved :: MIT License
Classifier: Programming Language :: Python :: 3
Classifier: Programming Language :: Python :: 3.9
